ddbox/.DS_Store
ddbox/__init__.py
ddbox/bin/.DS_Store
ddbox/bin/vina_1.2.5_linux_aarch64
ddbox/bin/vina_1.2.5_linux_x86_64
ddbox/bin/vina_1.2.5_mac_x86_64
ddbox/configs.py
ddbox/data/torch.py
ddbox/data/utils/__init__.py
ddbox/data/utils/loaders.py
ddbox/datasets/smallworld.py
ddbox/datasets/zinc.py
ddbox/docking/__init__.py
ddbox/docking/utils/__init__.py
ddbox/docking/utils/vina.py
ddbox/docking/vina.py
ddbox/metrics/.DS_Store
ddbox/metrics/SA_Score/__init__.py
ddbox/metrics/SA_Score/fpscores.pkl.gz
ddbox/metrics/SA_Score/sascorer.py
ddbox/metrics/__init__.py
ddbox/metrics/benchmarks/__init__.py
ddbox/metrics/benchmarks/moses.py
ddbox/metrics/data/mcf.csv
ddbox/metrics/data/wehi_pains.csv
ddbox/metrics/distribution_difference.py
ddbox/metrics/fcd.py
ddbox/metrics/fraction_passes.py
ddbox/metrics/fraction_unique.py
ddbox/metrics/fraction_valid.py
ddbox/metrics/fragment.py
ddbox/metrics/intdiv.py
ddbox/metrics/novelty.py
ddbox/metrics/scaffold.py
ddbox/metrics/snn.py
ddbox/metrics/utils.py
ddbox/molecule/__init__.py
ddbox/molecule/descriptors.py
ddbox/molecule/objects.py
ddbox/registries.py
ddbox/utils.py
ddbox-0.1.5.dist-info/METADATA
ddbox-0.1.5.dist-info/WHEEL
ddbox-0.1.5.dist-info/RECORD
