Metadata-Version: 2.1
Name: ddbox
Version: 0.1.5
Summary: 
Author: Azamat
Author-email: unawares15@gmail.com
Requires-Python: >=3.10,<4.0
Classifier: Programming Language :: Python :: 3
Classifier: Programming Language :: Python :: 3.10
Classifier: Programming Language :: Python :: 3.11
Requires-Dist: cryptography (>=41.0.2,<42.0.0)
Requires-Dist: fcd-torch (>=1.0.7,<2.0.0)
Requires-Dist: openbabel (>=3.1.1.1,<4.0.0.0)
Requires-Dist: pandas (>=2.0.1,<3.0.0)
Requires-Dist: pre-commit (>=2.20.0,<3.0.0)
Requires-Dist: rdkit (>=2023.3.1,<2024.0.0)
Requires-Dist: requests (>=2.30.0,<3.0.0)
Requires-Dist: torchvision (>=0.15.2,<0.16.0)
Requires-Dist: tqdm (>=4.65.0,<5.0.0)
Requires-Dist: urllib3 (==1.26.15)
